TkEasyGUI/__init__.py
TkEasyGUI/dialogs.py
TkEasyGUI/icon_default.py
TkEasyGUI/locale_easy.py
TkEasyGUI/utils.py
TkEasyGUI/version.py
TkEasyGUI/widgets.py
TkEasyGUI/widgets_framescrollable.py
TkEasyGUI/widgets_image.py
TkEasyGUI/widgets_window.py
tkeasygui-1.0.40.dist-info/licenses/LICENSE
tkeasygui-1.0.40.dist-info/METADATA
tkeasygui-1.0.40.dist-info/WHEEL
tkeasygui-1.0.40.dist-info/top_level.txt
tkeasygui-1.0.40.dist-info/RECORD
