Metadata-Version: 2.4
Name: TkEasyGUI
Version: 1.0.40
Summary: TkEasyGUI is simple GUI Library for Python3 with Tkinter
Author-email: kujirahand <web@kujirahand.com>
Maintainer-email: kujirahand <web@kujirahand.com>
License-Expression: MIT
Project-URL: Homepage, https://github.com/kujirahand/tkeasygui-python
Project-URL: Documentation, https://github.com/kujirahand/tkeasygui-python/blob/main/README.md
Project-URL: Repository, https://github.com/kujirahand/tkeasygui-python/
Project-URL: Issues, https://github.com/kujirahand/tkeasygui-python/issues
Project-URL: Changelog, https://github.com/kujirahand/tkeasygui-python/releases
Keywords: GUI,tkinter,TkEasyGUI
Classifier: Intended Audience :: Developers
Classifier: Programming Language :: Python :: 3
Classifier: Programming Language :: Python :: 3.9
Classifier: Programming Language :: Python :: 3.10
Classifier: Programming Language :: Python :: 3.11
Classifier: Programming Language :: Python :: 3.12
Classifier: Programming Language :: Python :: 3.13
Classifier: Programming Language :: Python :: 3 :: Only
Classifier: Topic :: Software Development :: User Interfaces
Requires-Python: >=3.9
License-File: LICENSE
Requires-Dist: Pillow>=11.3.0
Requires-Dist: pyperclip>=1.11.0
Dynamic: license-file
